[
    { "holiday_date": "2025-08-15", "description": "Independence Day" },
    { "holiday_date": "2025-08-28", "description": "Ganesh Chaturthi" },
    { "holiday_date": "2025-10-02", "description": "Gandhi Jayanti" },
    { "holiday_date": "2025-10-21", "description": "Diwali (Deepavali)" },
    { "holiday_date": "2025-12-25", "description": "Christmas" },
    { "holiday_date": "2026-01-01", "description": "New Year's Day" },
    { "holiday_date": "2026-01-26", "description": "Republic Day" },
    { "holiday_date": "2026-03-19", "description": "Ugadi / Gudi Padwa" },
    { "holiday_date": "2026-05-01", "description": "May Day (Labour Day)" }
  ]